openpgp_requests/__init__.py
openpgp_requests/openpgprequests.py
openpgp_requests-0.5.dist-info/LICENSE
openpgp_requests-0.5.dist-info/METADATA
openpgp_requests-0.5.dist-info/WHEEL
openpgp_requests-0.5.dist-info/top_level.txt
openpgp_requests-0.5.dist-info/RECORD
