Metadata-Version: 2.1
Name: openpgp-requests
Version: 0.5
Summary: A wrapper to the requests module adding OpenPGP support.
Home-page: https://github.com/buanzo/openpgp-requests
Author: Arturo "Buanzo" Busleiman
Author-email: buanzo@buanzo.com.ar
License: UNKNOWN
Platform: UNKNOWN
Requires-Python: >=3.6
Requires-Dist: requests (>=2.20.0)
Requires-Dist: gnupg (==2.3.1)
Requires-Dist: responses (==0.9.0)
